statz/__init__.py
statz/__main__.py
statz/benchmark.py
statz/cli.py
statz/dashboard.py
statz/file.py
statz/health.py
statz/network.py
statz/stats.py
statz/temp.py
statz/internal/_connectedDevicesMonitoring.py
statz/internal/_crossPlatform.py
statz/internal/_getLinuxInfo.py
statz/internal/_getMacInfo.py
statz/internal/_getWindowsInfo.py
statz-2.4.0.dist-info/licenses/LICENSE
statz-2.4.0.dist-info/METADATA
statz-2.4.0.dist-info/WHEEL
statz-2.4.0.dist-info/entry_points.txt
statz-2.4.0.dist-info/top_level.txt
statz-2.4.0.dist-info/RECORD
