Metadata-Version: 2.4
Name: statz
Version: 2.4.0
Summary: Cross-platform system stats made easy
Author-email: Swarit Narang <narangswarit02@gmail.com>
License: MIT
Project-URL: Homepage, https://github.com/hellonearth311/Statz
Project-URL: Bug Tracker, https://github.com/hellonearth311/Statz/issues
Classifier: Programming Language :: Python :: 3
Classifier: Operating System :: OS Independent
Classifier: License :: OSI Approved :: MIT License
Requires-Python: >=3.7
License-File: LICENSE
Requires-Dist: psutil
Requires-Dist: wmi
Requires-Dist: colorama
Requires-Dist: rich
Requires-Dist: speedtest-cli
Dynamic: license-file
